kieler_klighd_types/__about__.py
kieler_klighd_types/klighd/SKGraphSchema.py
kieler_klighd_types/klighd/SynthesisOptionSchema.py
kieler_klighd_types/klighd/__init__.py
kieler_klighd_types/klighd/actions/__init__.py
kieler_klighd_types/klighd/actions/checkImages.py
kieler_klighd_types/klighd/actions/checkedImages.py
kieler_klighd_types/klighd/actions/performAction.py
kieler_klighd_types/klighd/actions/refreshDiagram.py
kieler_klighd_types/klighd/actions/refreshLayout.py
kieler_klighd_types/klighd/actions/requestDiagramPiece.py
kieler_klighd_types/klighd/actions/setDiagramPiece.py
kieler_klighd_types/klighd/actions/setSyntheses.py
kieler_klighd_types/klighd/actions/setSynthesis.py
kieler_klighd_types/klighd/actions/storeImages.py
kieler_klighd_types/klighd/actions/updateOptions.py
kieler_klighd_types/klighd/messages/__init__.py
kieler_klighd_types/klighd/messages/diagramOptionsPerformAction.py
kieler_klighd_types/klighd/messages/diagramOptionsSetLayoutOptions.py
kieler_klighd_types/klighd/messages/diagramOptionsSetSynthesisOptions.py
kieler_klighd_types/klighd/messages/preferencesSetPreferences.py
kieler_klighd_types/lsp/__init__.py
kieler_klighd_types/lsp/generalSendMessage.py
kieler_klighd_types/lsp/initialize.py
kieler_klighd_types/lsp/message.py
kieler_klighd_types/lsp/range.py
kieler_klighd_types/lsp/requestMessage.py
kieler_klighd_types/lsp/responseMessage.py
kieler_klighd_types/lsp/textDocumentDocumentHighlight.py
kieler_klighd_types/sprotty/__init__.py
kieler_klighd_types/sprotty/diagramAccept.py
kieler_klighd_types/sprotty/diagramOpenInTextEditor.py
kieler_klighd_types/sprotty/actions/__init__.py
kieler_klighd_types/sprotty/actions/action.py
kieler_klighd_types/sprotty/actions/allSelected.py
kieler_klighd_types/sprotty/actions/elementSelected.py
kieler_klighd_types/sprotty/actions/fit.py
kieler_klighd_types/sprotty/actions/requestBounds.py
kieler_klighd_types/sprotty/actions/requestModel.py
kieler_klighd_types/sprotty/actions/setModel.py
kieler_klighd_types-0.0.4.dist-info/METADATA
kieler_klighd_types-0.0.4.dist-info/WHEEL
kieler_klighd_types-0.0.4.dist-info/licenses/LICENSE
kieler_klighd_types-0.0.4.dist-info/RECORD
