Metadata-Version: 2.4
Name: kieler-klighd-types
Version: 0.0.4
Summary: Types for creating language servers that can speak with klighd clients.
Project-URL: Homepage, https://github.com/kieler/kieler-klighd-types
Project-URL: Issues, https://github.com/kieler/kieler-klighd-types/issues
Author-email: Max Kasperowski <mka@informatik.uni-kiel.de>
License-Expression: MIT
License-File: LICENSE
Classifier: Development Status :: 4 - Beta
Classifier: Programming Language :: Python
Classifier: Programming Language :: Python :: 3.8
Classifier: Programming Language :: Python :: 3.9
Classifier: Programming Language :: Python :: 3.10
Classifier: Programming Language :: Python :: 3.11
Classifier: Programming Language :: Python :: 3.12
Classifier: Programming Language :: Python :: Implementation :: CPython
Classifier: Programming Language :: Python :: Implementation :: PyPy
Requires-Python: >=3.8
Requires-Dist: pydantic
